<?xml version="1.0" encoding="UTF-8"?>
<objects serializationModel="Studio.01.10.00">
    <object class="Event" id="{cccbf1a4-8cb5-412e-abda-e0764e20e8e1}">
        <property name="name">
            <value>ingame_music_loop_01</value>
        </property>
        <property name="outputFormat">
            <value>2</value>
        </property>
        <relationship name="folder">
            <destination>{13bbbe25-f7d6-4408-a363-abdc9f2df006}</destination>
        </relationship>
        <relationship name="mixer">
            <destination>{43719f1a-c301-4c5f-a7e0-26e7a30461a5}</destination>
        </relationship>
        <relationship name="masterTrack">
            <destination>{0833a84c-c0b4-45d8-8857-8e96f3086430}</destination>
        </relationship>
        <relationship name="mixerInput">
            <destination>{87ef9947-a7c3-4121-8a01-eee7e0b2e02d}</destination>
        </relationship>
        <relationship name="automatableProperties">
            <destination>{dbbd0074-2a55-487b-9308-8b6145c6e272}</destination>
        </relationship>
        <relationship name="markerTracks">
            <destination>{7a70c925-31f6-43b1-b3ee-3e4d5f19e734}</destination>
        </relationship>
        <relationship name="groupTracks">
            <destination>{d8a8e9d5-25b3-4a23-ae30-ab4838bbe9c0}</destination>
        </relationship>
        <relationship name="timeline">
            <destination>{d9b43439-9df8-44d9-9861-8a2d55e9cf06}</destination>
        </relationship>
        <relationship name="banks">
            <destination>{ea456630-c3c8-43d1-89cd-0b2c1da55881}</destination>
        </relationship>
    </object>
    <object class="EventMixer" id="{43719f1a-c301-4c5f-a7e0-26e7a30461a5}">
        <relationship name="masterBus">
            <destination>{bdd5e42e-2587-4feb-94a1-9d93ebe9fd1b}</destination>
        </relationship>
    </object>
    <object class="MasterTrack" id="{0833a84c-c0b4-45d8-8857-8e96f3086430}">
        <relationship name="mixerGroup">
            <destination>{bdd5e42e-2587-4feb-94a1-9d93ebe9fd1b}</destination>
        </relationship>
    </object>
    <object class="MixerInput" id="{87ef9947-a7c3-4121-8a01-eee7e0b2e02d}">
        <relationship name="effectChain">
            <destination>{61251084-3f4e-42b1-870a-849761a11ec6}</destination>
        </relationship>
        <relationship name="panner">
            <destination>{dcfb4df8-3287-4f72-9339-d8b582b49889}</destination>
        </relationship>
        <relationship name="output">
            <destination>{10a012c0-6a72-429d-96ea-59de21308e1b}</destination>
        </relationship>
    </object>
    <object class="EventAutomatableProperties" id="{dbbd0074-2a55-487b-9308-8b6145c6e272}"/>
    <object class="MarkerTrack" id="{7a70c925-31f6-43b1-b3ee-3e4d5f19e734}"/>
    <object class="GroupTrack" id="{d8a8e9d5-25b3-4a23-ae30-ab4838bbe9c0}">
        <relationship name="modules">
            <destination>{accd2088-410c-4739-91f3-45cde8d1ba3f}</destination>
        </relationship>
        <relationship name="mixerGroup">
            <destination>{a9097be8-44c8-4587-8060-de202ca4a4a8}</destination>
        </relationship>
    </object>
    <object class="Timeline" id="{d9b43439-9df8-44d9-9861-8a2d55e9cf06}">
        <relationship name="modules">
            <destination>{accd2088-410c-4739-91f3-45cde8d1ba3f}</destination>
        </relationship>
        <relationship name="markers">
            <destination>{ee850c79-fa50-42ea-87b6-faf04eb2b984}</destination>
        </relationship>
    </object>
    <object class="EventMixerMaster" id="{bdd5e42e-2587-4feb-94a1-9d93ebe9fd1b}">
        <relationship name="effectChain">
            <destination>{264ca43a-6350-49f1-9d13-cff44380cd8c}</destination>
        </relationship>
        <relationship name="panner">
            <destination>{d064e424-d28b-40b4-a766-968bd06d4362}</destination>
        </relationship>
        <relationship name="mixer">
            <destination>{43719f1a-c301-4c5f-a7e0-26e7a30461a5}</destination>
        </relationship>
    </object>
    <object class="MixerBusEffectChain" id="{61251084-3f4e-42b1-870a-849761a11ec6}">
        <relationship name="effects">
            <destination>{6d82ecbb-3820-4f40-b012-b2953fe88af0}</destination>
        </relationship>
    </object>
    <object class="MixerBusPanner" id="{dcfb4df8-3287-4f72-9339-d8b582b49889}"/>
    <object class="SingleSound" id="{accd2088-410c-4739-91f3-45cde8d1ba3f}">
        <property name="length">
            <value>93.604058956916106</value>
        </property>
        <relationship name="audioFile">
            <destination>{d867da11-c1ea-407b-bcad-0b1691d60868}</destination>
        </relationship>
    </object>
    <object class="EventMixerGroup" id="{a9097be8-44c8-4587-8060-de202ca4a4a8}">
        <property name="volume">
            <value>-15</value>
        </property>
        <property name="name">
            <value>Audio 1</value>
        </property>
        <relationship name="effectChain">
            <destination>{cb6f1a33-e40a-4052-b342-93a081461ae2}</destination>
        </relationship>
        <relationship name="panner">
            <destination>{d45c973a-689e-4858-ae2c-d84221d7ab3b}</destination>
        </relationship>
        <relationship name="output">
            <destination>{bdd5e42e-2587-4feb-94a1-9d93ebe9fd1b}</destination>
        </relationship>
    </object>
    <object class="LoopRegion" id="{ee850c79-fa50-42ea-87b6-faf04eb2b984}">
        <property name="position">
            <value>0</value>
        </property>
        <property name="length">
            <value>93.604058956916106</value>
        </property>
        <relationship name="timeline">
            <destination>{d9b43439-9df8-44d9-9861-8a2d55e9cf06}</destination>
        </relationship>
        <relationship name="markerTrack">
            <destination>{7a70c925-31f6-43b1-b3ee-3e4d5f19e734}</destination>
        </relationship>
    </object>
    <object class="MixerBusEffectChain" id="{264ca43a-6350-49f1-9d13-cff44380cd8c}">
        <relationship name="effects">
            <destination>{31e54895-ee48-41f0-8cb6-591b33590dc0}</destination>
            <destination>{f550c432-fa2c-4868-942c-4ea5c93d3917}</destination>
        </relationship>
    </object>
    <object class="MixerBusPanner" id="{d064e424-d28b-40b4-a766-968bd06d4362}"/>
    <object class="MixerBusFader" id="{6d82ecbb-3820-4f40-b012-b2953fe88af0}"/>
    <object class="MixerBusEffectChain" id="{cb6f1a33-e40a-4052-b342-93a081461ae2}">
        <relationship name="effects">
            <destination>{53520e44-657d-4a98-a827-637e3bcd7d3e}</destination>
        </relationship>
    </object>
    <object class="MixerBusPanner" id="{d45c973a-689e-4858-ae2c-d84221d7ab3b}"/>
    <object class="MixerBusFader" id="{31e54895-ee48-41f0-8cb6-591b33590dc0}"/>
    <object class="SpatialiserEffect" id="{f550c432-fa2c-4868-942c-4ea5c93d3917}"/>
    <object class="MixerBusFader" id="{53520e44-657d-4a98-a827-637e3bcd7d3e}"/>
</objects>
